pydidas/__init__.py
pydidas/initialize.py
pydidas/logging_level.py
pydidas/version.py
pydidas/apps/__init__.py
pydidas/apps/composite_creator_app.py
pydidas/apps/directory_spy_app.py
pydidas/apps/execute_workflow_app.py
pydidas/apps/execute_workflow_runner.py
pydidas/apps/parsers/__init__.py
pydidas/apps/parsers/_composite_creator_app_parser.py
pydidas/apps/parsers/_directory_spy_app_parser.py
pydidas/apps/parsers/_execute_workflow_app_parser.py
pydidas/contexts/__init__.py
pydidas/contexts/diff_exp/__init__.py
pydidas/contexts/diff_exp/diff_exp.py
pydidas/contexts/diff_exp/diff_exp_context.py
pydidas/contexts/diff_exp/diff_exp_io.py
pydidas/contexts/diff_exp/diff_exp_io_base.py
pydidas/contexts/diff_exp/diff_exp_io_hdf5.py
pydidas/contexts/diff_exp/diff_exp_io_poni.py
pydidas/contexts/diff_exp/diff_exp_io_yaml.py
pydidas/contexts/scan/__init__.py
pydidas/contexts/scan/scan.py
pydidas/contexts/scan/scan_context.py
pydidas/contexts/scan/scan_io.py
pydidas/contexts/scan/scan_io_base.py
pydidas/contexts/scan/scan_io_fio.py
pydidas/contexts/scan/scan_io_hdf5.py
pydidas/contexts/scan/scan_io_yaml.py
pydidas/core/__init__.py
pydidas/core/base_app.py
pydidas/core/dataset.py
pydidas/core/exceptions.py
pydidas/core/generic_parameters.py
pydidas/core/hdf5_key.py
pydidas/core/object_with_parameter_collection.py
pydidas/core/parameter.py
pydidas/core/parameter_collection.py
pydidas/core/parameter_collection_mixin.py
pydidas/core/pydidas_q_settings.py
pydidas/core/pydidas_q_settings_mixin.py
pydidas/core/singleton_context_object.py
pydidas/core/singleton_object.py
pydidas/core/constants/__init__.py
pydidas/core/constants/colors.py
pydidas/core/constants/constants.py
pydidas/core/constants/file_extensions.py
pydidas/core/constants/gui_constants.py
pydidas/core/constants/image_ops.py
pydidas/core/constants/links.py
pydidas/core/constants/main_menu_actions.py
pydidas/core/constants/main_window_menu_entries.py
pydidas/core/constants/numpy_names.py
pydidas/core/constants/paths.py
pydidas-25.5.16.dist-info/licenses/LICENSE.md
pydidas-25.5.16.dist-info/METADATA
pydidas-25.5.16.dist-info/WHEEL
pydidas-25.5.16.dist-info/entry_points.txt
pydidas-25.5.16.dist-info/top_level.txt
pydidas-25.5.16.dist-info/RECORD
