Metadata-Version: 2.4
Name: pydidas
Version: 25.5.16
Summary: pydidas - the PYthon DIffraction Data Analysis Suite
Author: Malte Storm
License-Expression: GPL-3.0-only
Project-URL: homepage, https://pydidas.hereon.de/
Project-URL: documentation, https://hereon-gems.github.io/pydidas
Project-URL: repository, https://github.com/hereon-GEMS/pydidas
Project-URL: changelog, https://github.com/hereon-GEMS/pydidas/blob/master/CHANGELOG.md
Keywords: X-ray diffraction,XRD,WAXS,SAXS
Classifier: Development Status :: 5 - Production/Stable
Classifier: Programming Language :: Python :: 3 :: Only
Classifier: Programming Language :: Python :: 3.11
Classifier: Programming Language :: Python :: 3.12
Classifier: Topic :: Scientific/Engineering
Classifier: Topic :: Scientific/Engineering :: Image Processing
Classifier: Topic :: Scientific/Engineering :: Physics
Requires-Python: <3.13,>=3.11
License-File: LICENSE.md
Requires-Dist: accessible-pygments==0.0.5
Requires-Dist: alabaster==1.0.0
Requires-Dist: babel==2.17.0
Requires-Dist: beautifulsoup4==4.13.4
Requires-Dist: build==1.2.2.post1
Requires-Dist: certifi==2025.4.26
Requires-Dist: charset-normalizer==3.4.2
Requires-Dist: colorama==0.4.6
Requires-Dist: contourpy==1.3.2
Requires-Dist: cycler==0.12.1
Requires-Dist: docutils==0.21.2
Requires-Dist: fabio==2024.9.0
Requires-Dist: fonttools==4.58.0
Requires-Dist: h5py==3.13.0
Requires-Dist: hdf5plugin==5.1.0
Requires-Dist: idna==3.10
Requires-Dist: imagecodecs==2025.3.30
Requires-Dist: imageio==2.37.0
Requires-Dist: imagesize==1.4.1
Requires-Dist: jinja2==3.1.6
Requires-Dist: kiwisolver==1.4.8
Requires-Dist: lazy-loader==0.4
Requires-Dist: lxml==5.4.0
Requires-Dist: markupsafe==3.0.2
Requires-Dist: matplotlib==3.10.3
Requires-Dist: networkx==3.4.2
Requires-Dist: numexpr==2.10.2
Requires-Dist: numpy==2.2.5
Requires-Dist: packaging==25.0
Requires-Dist: pillow==11.2.1
Requires-Dist: platformdirs==4.3.8
Requires-Dist: pydata-sphinx-theme==0.16.1
Requires-Dist: pyfai==2025.3.0
Requires-Dist: pygments==2.19.1
Requires-Dist: pyopencl==2025.1
Requires-Dist: pyparsing==3.2.3
Requires-Dist: pyproject-hooks==1.2.0
Requires-Dist: pyqt5==5.15.11
Requires-Dist: pyqt5-qt5==5.15.2; sys_platform != "darwin"
Requires-Dist: pyqt5-qt5==5.15.14; sys_platform == "darwin"
Requires-Dist: pyqt5-sip==12.17.0
Requires-Dist: pyside6==6.9.0
Requires-Dist: pyside6-addons==6.9.0
Requires-Dist: pyside6-essentials==6.9.0
Requires-Dist: python-dateutil==2.9.0.post0
Requires-Dist: pytools==2025.1.4
Requires-Dist: pyyaml==6.0.2
Requires-Dist: qtpy==2.4.3
Requires-Dist: requests==2.32.3
Requires-Dist: roman-numerals-py==3.1.0
Requires-Dist: scikit-image==0.25.2
Requires-Dist: scipy==1.15.3
Requires-Dist: shiboken6==6.9.0
Requires-Dist: silx==2.1.1
Requires-Dist: siphash24==1.7
Requires-Dist: six==1.17.0
Requires-Dist: snowballstemmer==3.0.1
Requires-Dist: soupsieve==2.7
Requires-Dist: sphinx==8.2.3
Requires-Dist: sphinx-copybutton==0.5.2
Requires-Dist: sphinx-design==0.6.1
Requires-Dist: sphinxcontrib-applehelp==2.0.0
Requires-Dist: sphinxcontrib-devhelp==2.0.0
Requires-Dist: sphinxcontrib-htmlhelp==2.1.0
Requires-Dist: sphinxcontrib-jsmath==1.0.1
Requires-Dist: sphinxcontrib-qthelp==2.0.0
Requires-Dist: sphinxcontrib-serializinghtml==2.0.0
Requires-Dist: tifffile==2025.5.10
Requires-Dist: typing-extensions==4.13.2
Requires-Dist: urllib3==2.4.0
Provides-Extra: dev
Requires-Dist: black>=24.4.0; extra == "dev"
Requires-Dist: flake8>=7.0.0; extra == "dev"
Requires-Dist: ipython>=8.20; extra == "dev"
Requires-Dist: isort>=5.13.2; extra == "dev"
Requires-Dist: GitPython>=3.1.43; extra == "dev"
Requires-Dist: pip-tools>=7.4.1; extra == "dev"
Requires-Dist: reuse>=4.0.3; extra == "dev"
Requires-Dist: ruff>=0.9.1; extra == "dev"
Requires-Dist: pytest>=8.3.0; extra == "dev"
Requires-Dist: PyQt5-stubs>=5.15.6; extra == "dev"
Dynamic: license-file
